FPGA/GateKeeper/srcs/GateKeeper.v
`timescale 1ns / 1ps
//////////////////////////////////////////////////////////////////////////////////
// Company: 
// Engineer: 
// 
// Create Date: 03/25/2025 01:38:00 PM
// Design Name: 
// Module Name: GateKeeper
// Project Name: 
// Target Devices: 
// Tool Versions: 
// Description: 
// 
// Dependencies: 
// 
// Revision:
// Revision 0.01 - File Created
// Additional Comments:
// 
//////////////////////////////////////////////////////////////////////////////////


module GateKeeper(
    input wire clk,
    input wire enable,
    input wire [15:0] window,
    input wire [7:0] pulseShaper_width,
    input wire det_in,
    output wire det_out,
    reg GateKeeper = 1'b1 // GateKeeper is used to vaariable the output of the module
);



reg [15:0] c = 16'h0000; // c counts the number of clock cycles since last detection
reg det_in_prev = 1'b0; // det_in_prev is used to store the previous value of det_in
reg [1:0] state = 2'd0; 
// reg GateKeeper = 1'b1; // GateKeeper is used to variable the output of the module


assign det_out = (GateKeeper) ? det_in:1'b0; // main assignation

//Every 2.5 ns logic is evaluated
always@(posedge clk) begin

    det_in_prev <= det_in; // store the previous value of det_in

    if(enable)begin//from GUI
        case(state)
            0:begin
                if(det_in)begin//input signal
                    c           <= 16'd1; // reset counter every time a detection is made
                    state       <= 1; // jump to state 1
                end
            end

            1:begin
                if(c<({8'd0,pulseShaper_width}))begin //
                    c               <= c + 16'd1; // increment c
                end
                else begin // if c is equal to pulseShaper_width, disable det_out 
                    c               <= 16'd1;
                    GateKeeper      <= 1'b0; // disable det_out
                    state           <= 2; // jump to state 2
                end
            end

            2:begin
                if(c<(window))begin // if c is less than window, increment c
                    c               <= c + 16'd1; // increment c
                end
                else begin // if c is equal to window, disable det_out
                    if(det_in)begin
                        c               <= 16'd1;
                        GateKeeper      <= 1'b0; // enable det_out
                        state           <= 3; // jump to state 3
                    end
                    else begin
                        c               <= 16'd0;
                        GateKeeper      <= 1'b1; // enable det_out
                        state           <= 0; // jump to state 0
                    end 
                end
            end

            3:begin
                if(c<({8'd0,pulseShaper_width}))begin //
                    c               <= c + 16'd1; // increment c
                end
                else begin // if c is equal to pulseShaper_width, disable det_out 
                    c               <= 16'd0;
                    GateKeeper      <= 1'b1; // disable det_out
                    state           <= 0; // jump to state 0
                end
            end

        endcase
    end

    else begin // when the module is not enabled, det_in is bypassed to det_out
        GateKeeper             <= 1'b1;// enable det_out
    end

end


endmodule

FPGA/GateKeeper/srcs/tb_GateKeeper.v
`timescale 1ns / 1ps
//////////////////////////////////////////////////////////////////////////////////
// Company: 
// Engineer: 
// 
// Create Date: 03/25/2025 02:57:35 PM
// Design Name: 
// Module Name: tb_GateKeeper
// Project Name: 
// Target Devices: 
// Tool Versions: 
// Description: 
// 
// Dependencies: 
// 
// Revision:
// Revision 0.01 - File Created
// Additional Comments:
// 
//////////////////////////////////////////////////////////////////////////////////


module tb_GateKeeper();
    // Testbench Signals
    reg clk = 0;
    reg enable = 1;
    reg [15:0] window = 16'd6;
    reg [7:0] pulseShaper_width = 8'd20;
    reg det_in = 0;
    wire det_out;
    wire GateKeeper;
    
    // Clock Generation (400 MHz -> 2.5 ns period)
    always #1.25 clk = ~clk;
    
    // Instantiate DUT (Device Under Test)
    GateKeeper GateKeeper0 (
        .clk(clk),
        .enable(enable),
        .window(window),
        .pulseShaper_width(pulseShaper_width),
        .det_in(det_in),
        .det_out(det_out),
        .GateKeeper(GateKeeper)
    );
    
    // Stimulus
    initial begin
        $dumpfile("tb_GateKeeper.vcd");
        $dumpvars(0, tb_GateKeeper);
        
        #15;
        det_in = 1;
        #50;
        det_in = 0;
        
        #50;
        det_in = 1;
        #50;
        det_in = 0;

        #13.0;
        det_in = 1;
        #50;
        det_in = 0;
        
        #14.0;
        det_in = 1;
        #50;
        det_in = 0;

        #15.0;
        det_in = 1;
        #50;
        det_in = 0;
        
        #16.0;
        det_in = 1;
        #50;
        det_in = 0;

        #17.0;
        det_in = 1;
        #50;
        det_in = 0;

        #18.0;
        det_in = 1;
        #50;
        det_in = 0;

        #19.0;
        det_in = 1;
        #50;
        det_in = 0;

        

        $finish;
    end
    
endmodule

FPGA/GateKeeper/GateKeeper.sim/sim_1/behav/xsim/tb_GateKeeper.vcd
$date
   Thu Apr  3 16:15:15 2025
$end

$version
  2023.2
  $dumpfile ("tb_GateKeeper.vcd") 
$end

$timescale
  1ps
$end

$scope module tb_GateKeeper $end
$var reg 1 ! clk $end
$var reg 1 " enable $end
$var reg 16 # window [15:0] $end
$var reg 8 $ pulseShaper_width [7:0] $end
$var reg 1 % det_in $end
$var wire 1 & det_out $end
$var wire 1 ' GateKeeper $end
$scope module GateKeeper0 $end
$var wire 1 ( clk $end
$var wire 1 ) enable $end
$var wire 16 * window [15:0] $end
$var wire 8 + pulseShaper_width [7:0] $end
$var wire 1 , det_in $end
$var wire 1 & det_out $end
$var reg 1 - GateKeeper $end
$var reg 16 . c [15:0] $end
$var reg 1 / det_in_prev $end
$var reg 2 0 state [1:0] $end
$upscope $end
$upscope $end
$enddefinitions $end

#0
$dumpvars
0!
1"
b110 #
b10100 $
0%
0&
1'
0(
1)
b110 *
b10100 +
0,
1-
b0 .
0/
b0 0
$end

#1250
1!
1(

#2500
0!
0(

#3750
1!
1(

#5000
0!
0(

#6250
1!
1(

#7500
0!
0(

#8750
1!
1(

#10000
0!
0(

#11250
1!
1(

#12500
0!
0(

#13750
1!
1(

#15000
0!
1%
1&
0(
1,

#16250
1!
1(
b1 .
1/
b1 0

#17500
0!
0(

#18750
1!
1(
b10 .

#20000
0!
0(

#21250
1!
1(
b11 .

#22500
0!
0(

#23750
1!
1(
b100 .

#25000
0!
0(

#26250
1!
1(
b101 .

#27500
0!
0(

#28750
1!
1(
b110 .

#30000
0!
0(

#31250
1!
1(
b111 .

#32500
0!
0(

#33750
1!
1(
b1000 .

#35000
0!
0(

#36250
1!
1(
b1001 .

#37500
0!
0(

#38750
1!
1(
b1010 .

#40000
0!
0(

#41250
1!
1(
b1011 .

#42500
0!
0(

#43750
1!
1(
b1100 .

#45000
0!
0(

#46250
1!
1(
b1101 .

#47500
0!
0(

#48750
1!
1(
b1110 .

#50000
0!
0(

#51250
1!
1(
b1111 .

#52500
0!
0(

#53750
1!
1(
b10000 .

#55000
0!
0(

#56250
1!
1(
b10001 .

#57500
0!
0(

#58750
1!
1(
b10010 .

#60000
0!
0(

#61250
1!
1(
b10011 .

#62500
0!
0(

#63750
1!
1(
b10100 .

#65000
0!
0%
0&
0(
0,

#66250
1!
0'
1(
0-
b1 .
0/
b10 0

#67500
0!
0(

#68750
1!
1(
b10 .

#70000
0!
0(

#71250
1!
1(
b11 .

#72500
0!
0(

#73750
1!
1(
b100 .

#75000
0!
0(

#76250
1!
1(
b101 .

#77500
0!
0(

#78750
1!
1(
b110 .

#80000
0!
0(

#81250
1!
1'
1(
1-
b0 .
b0 0

#82500
0!
0(

#83750
1!
1(

#85000
0!
0(

#86250
1!
1(

#87500
0!
0(

#88750
1!
1(

#90000
0!
0(

#91250
1!
1(

#92500
0!
0(

#93750
1!
1(

#95000
0!
0(

#96250
1!
1(

#97500
0!
0(

#98750
1!
1(

#100000
0!
0(

#101250
1!
1(

#102500
0!
0(

#103750
1!
1(

#105000
0!
0(

#106250
1!
1(

#107500
0!
0(

#108750
1!
1(

#110000
0!
0(

#111250
1!
1(

#112500
0!
0(

#113750
1!
1(

#115000
0!
1%
1&
0(
1,

#116250
1!
1(
b1 .
1/
b1 0

#117500
0!
0(

#118750
1!
1(
b10 .

#120000
0!
0(

#121250
1!
1(
b11 .

#122500
0!
0(

#123750
1!
1(
b100 .

#125000
0!
0(

#126250
1!
1(
b101 .

#127500
0!
0(

#128750
1!
1(
b110 .

#130000
0!
0(

#131250
1!
1(
b111 .

#132500
0!
0(

#133750
1!
1(
b1000 .

#135000
0!
0(

#136250
1!
1(
b1001 .

#137500
0!
0(

#138750
1!
1(
b1010 .

#140000
0!
0(

#141250
1!
1(
b1011 .

#142500
0!
0(

#143750
1!
1(
b1100 .

#145000
0!
0(

#146250
1!
1(
b1101 .

#147500
0!
0(

#148750
1!
1(
b1110 .

#150000
0!
0(

#151250
1!
1(
b1111 .

#152500
0!
0(

#153750
1!
1(
b10000 .

#155000
0!
0(

#156250
1!
1(
b10001 .

#157500
0!
0(

#158750
1!
1(
b10010 .

#160000
0!
0(

#161250
1!
1(
b10011 .

#162500
0!
0(

#163750
1!
1(
b10100 .

#165000
0!
0%
0&
0(
0,

#166250
1!
0'
1(
0-
b1 .
0/
b10 0

#167500
0!
0(

#168750
1!
1(
b10 .

#170000
0!
0(

#171250
1!
1(
b11 .

#172500
0!
0(

#173750
1!
1(
b100 .

#175000
0!
0(

#176250
1!
1(
b101 .

#177500
0!
0(

#178000
1%
1,

#178750
1!
1(
b110 .
1/

#180000
0!
0(

#181250
1!
1(
b1 .
b11 0

#182500
0!
0(

#183750
1!
1(
b10 .

#185000
0!
0(

#186250
1!
1(
b11 .

#187500
0!
0(

#188750
1!
1(
b100 .

#190000
0!
0(

#191250
1!
1(
b101 .

#192500
0!
0(

#193750
1!
1(
b110 .

#195000
0!
0(

#196250
1!
1(
b111 .

#197500
0!
0(

#198750
1!
1(
b1000 .

#200000
0!
0(

#201250
1!
1(
b1001 .

#202500
0!
0(

#203750
1!
1(
b1010 .

#205000
0!
0(

#206250
1!
1(
b1011 .

#207500
0!
0(

#208750
1!
1(
b1100 .

#210000
0!
0(

#211250
1!
1(
b1101 .

#212500
0!
0(

#213750
1!
1(
b1110 .

#215000
0!
0(

#216250
1!
1(
b1111 .

#217500
0!
0(

#218750
1!
1(
b10000 .

#220000
0!
0(

#221250
1!
1(
b10001 .

#222500
0!
0(

#223750
1!
1(
b10010 .

#225000
0!
0(

#226250
1!
1(
b10011 .

#227500
0!
0(

#228000
0%
0,

#228750
1!
1(
b10100 .
0/

#230000
0!
0(

#231250
1!
1'
1(
1-
b0 .
b0 0

#232500
0!
0(

#233750
1!
1(

#235000
0!
0(

#236250
1!
1(

#237500
0!
0(

#238750
1!
1(

#240000
0!
0(

#241250
1!
1(

#242000
1%
1&
1,

#242500
0!
0(

#243750
1!
1(
b1 .
1/
b1 0

#245000
0!
0(

#246250
1!
1(
b10 .

#247500
0!
0(

#248750
1!
1(
b11 .

#250000
0!
0(

#251250
1!
1(
b100 .

#252500
0!
0(

#253750
1!
1(
b101 .

#255000
0!
0(

#256250
1!
1(
b110 .

#257500
0!
0(

#258750
1!
1(
b111 .

#260000
0!
0(

#261250
1!
1(
b1000 .

#262500
0!
0(

#263750
1!
1(
b1001 .

#265000
0!
0(

#266250
1!
1(
b1010 .

#267500
0!
0(

#268750
1!
1(
b1011 .

#270000
0!
0(

#271250
1!
1(
b1100 .

#272500
0!
0(

#273750
1!
1(
b1101 .

#275000
0!
0(

#276250
1!
1(
b1110 .

#277500
0!
0(

#278750
1!
1(
b1111 .

#280000
0!
0(

#281250
1!
1(
b10000 .

#282500
0!
0(

#283750
1!
1(
b10001 .

#285000
0!
0(

#286250
1!
1(
b10010 .

#287500
0!
0(

#288750
1!
1(
b10011 .

#290000
0!
0(

#291250
1!
1(
b10100 .

#292000
0%
0&
0,

#292500
0!
0(

#293750
1!
0'
1(
0-
b1 .
0/
b10 0

#295000
0!
0(

#296250
1!
1(
b10 .

#297500
0!
0(

#298750
1!
1(
b11 .

#300000
0!
0(

#301250
1!
1(
b100 .

#302500
0!
0(

#303750
1!
1(
b101 .

#305000
0!
0(

#306250
1!
1(
b110 .

#307000
1%
1,

#307500
0!
0(

#308750
1!
1(
b1 .
1/
b11 0

#310000
0!
0(

#311250
1!
1(
b10 .

#312500
0!
0(

#313750
1!
1(
b11 .

#315000
0!
0(

#316250
1!
1(
b100 .

#317500
0!
0(

#318750
1!
1(
b101 .

#320000
0!
0(

#321250
1!
1(
b110 .

#322500
0!
0(

#323750
1!
1(
b111 .

#325000
0!
0(

#326250
1!
1(
b1000 .

#327500
0!
0(

#328750
1!
1(
b1001 .

#330000
0!
0(

#331250
1!
1(
b1010 .

#332500
0!
0(

#333750
1!
1(
b1011 .

#335000
0!
0(

#336250
1!
1(
b1100 .

#337500
0!
0(

#338750
1!
1(
b1101 .

#340000
0!
0(

#341250
1!
1(
b1110 .

#342500
0!
0(

#343750
1!
1(
b1111 .

#345000
0!
0(

#346250
1!
1(
b10000 .

#347500
0!
0(

#348750
1!
1(
b10001 .

#350000
0!
0(

#351250
1!
1(
b10010 .

#352500
0!
0(

#353750
1!
1(
b10011 .

#355000
0!
0(

#356250
1!
1(
b10100 .

#357000
0%
0,

#357500
0!
0(

#358750
1!
1'
1(
1-
b0 .
0/
b0 0

#360000
0!
0(

#361250
1!
1(

#362500
0!
0(

#363750
1!
1(

#365000
0!
0(

#366250
1!
1(

#367500
0!
0(

#368750
1!
1(

#370000
0!
0(

#371250
1!
1(

#372500
0!
0(

#373000
1%
1&
1,

#373750
1!
1(
b1 .
1/
b1 0

#375000
0!
0(

#376250
1!
1(
b10 .

#377500
0!
0(

#378750
1!
1(
b11 .

#380000
0!
0(

#381250
1!
1(
b100 .

#382500
0!
0(

#383750
1!
1(
b101 .

#385000
0!
0(

#386250
1!
1(
b110 .

#387500
0!
0(

#388750
1!
1(
b111 .

#390000
0!
0(

#391250
1!
1(
b1000 .

#392500
0!
0(

#393750
1!
1(
b1001 .

#395000
0!
0(

#396250
1!
1(
b1010 .

#397500
0!
0(

#398750
1!
1(
b1011 .

#400000
0!
0(

#401250
1!
1(
b1100 .

#402500
0!
0(

#403750
1!
1(
b1101 .

#405000
0!
0(

#406250
1!
1(
b1110 .

#407500
0!
0(

#408750
1!
1(
b1111 .

#410000
0!
0(

#411250
1!
1(
b10000 .

#412500
0!
0(

#413750
1!
1(
b10001 .

#415000
0!
0(

#416250
1!
1(
b10010 .

#417500
0!
0(

#418750
1!
1(
b10011 .

#420000
0!
0(

#421250
1!
1(
b10100 .

#422500
0!
0(

#423000
0%
0&
0,

#423750
1!
0'
1(
0-
b1 .
0/
b10 0

#425000
0!
0(

#426250
1!
1(
b10 .

#427500
0!
0(

#428750
1!
1(
b11 .

#430000
0!
0(

#431250
1!
1(
b100 .

#432500
0!
0(

#433750
1!
1(
b101 .

#435000
0!
0(

#436250
1!
1(
b110 .

#437500
0!
0(

#438750
1!
1'
1(
1-
b0 .
b0 0

#440000
0!
1%
1&
0(
1,

#441250
1!
1(
b1 .
1/
b1 0

#442500
0!
0(

#443750
1!
1(
b10 .

#445000
0!
0(

#446250
1!
1(
b11 .

#447500
0!
0(

#448750
1!
1(
b100 .

#450000
0!
0(

#451250
1!
1(
b101 .

#452500
0!
0(

#453750
1!
1(
b110 .

#455000
0!
0(

#456250
1!
1(
b111 .

#457500
0!
0(

#458750
1!
1(
b1000 .

#460000
0!
0(

#461250
1!
1(
b1001 .

#462500
0!
0(

#463750
1!
1(
b1010 .

#465000
0!
0(

#466250
1!
1(
b1011 .

#467500
0!
0(

#468750
1!
1(
b1100 .

#470000
0!
0(

#471250
1!
1(
b1101 .

#472500
0!
0(

#473750
1!
1(
b1110 .

#475000
0!
0(

#476250
1!
1(
b1111 .

#477500
0!
0(

#478750
1!
1(
b10000 .

#480000
0!
0(

#481250
1!
1(
b10001 .

#482500
0!
0(

#483750
1!
1(
b10010 .

#485000
0!
0(

#486250
1!
1(
b10011 .

#487500
0!
0(

#488750
1!
1(
b10100 .

#490000
0!
0%
0&
0(
0,

#491250
1!
0'
1(
0-
b1 .
0/
b10 0

#492500
0!
0(

#493750
1!
1(
b10 .

#495000
0!
0(

#496250
1!
1(
b11 .

#497500
0!
0(

#498750
1!
1(
b100 .

#500000
0!
0(

#501250
1!
1(
b101 .

#502500
0!
0(

#503750
1!
1(
b110 .

#505000
0!
0(

#506250
1!
1'
1(
1-
b0 .
b0 0

#507500
0!
0(

#508000
1%
1&
1,

#508750
1!
1(
b1 .
1/
b1 0

#510000
0!
0(

#511250
1!
1(
b10 .

#512500
0!
0(

#513750
1!
1(
b11 .

#515000
0!
0(

#516250
1!
1(
b100 .

#517500
0!
0(

#518750
1!
1(
b101 .

#520000
0!
0(

#521250
1!
1(
b110 .

#522500
0!
0(

#523750
1!
1(
b111 .

#525000
0!
0(

#526250
1!
1(
b1000 .

#527500
0!
0(

#528750
1!
1(
b1001 .

#530000
0!
0(

#531250
1!
1(
b1010 .

#532500
0!
0(

#533750
1!
1(
b1011 .

#535000
0!
0(

#536250
1!
1(
b1100 .

#537500
0!
0(

#538750
1!
1(
b1101 .

#540000
0!
0(

#541250
1!
1(
b1110 .

#542500
0!
0(

#543750
1!
1(
b1111 .

#545000
0!
0(

#546250
1!
1(
b10000 .

#547500
0!
0(

#548750
1!
1(
b10001 .

#550000
0!
0(

#551250
1!
1(
b10010 .

#552500
0!
0(

#553750
1!
1(
b10011 .

#555000
0!
0(

#556250
1!
1(
b10100 .

#557500
0!
0(

#558000
0%
0&
0,

#558750
1!
0'
1(
0-
b1 .
0/
b10 0

#560000
0!
0(

#561250
1!
1(
b10 .

#562500
0!
0(

#563750
1!
1(
b11 .

#565000
0!
0(

#566250
1!
1(
b100 .

#567500
0!
0(

#568750
1!
1(
b101 .

#570000
0!
0(

#571250
1!
1(
b110 .

#572500
0!
0(

#573750
1!
1'
1(
1-
b0 .
b0 0

#575000
0!
0(

#576250
1!
1(

#577000
1%
1&
1,

#577500
0!
0(

#578750
1!
1(
b1 .
1/
b1 0

#580000
0!
0(

#581250
1!
1(
b10 .

#582500
0!
0(

#583750
1!
1(
b11 .

#585000
0!
0(

#586250
1!
1(
b100 .

#587500
0!
0(

#588750
1!
1(
b101 .

#590000
0!
0(

#591250
1!
1(
b110 .

#592500
0!
0(

#593750
1!
1(
b111 .

#595000
0!
0(

#596250
1!
1(
b1000 .

#597500
0!
0(

#598750
1!
1(
b1001 .

#600000
0!
0(

#601250
1!
1(
b1010 .

#602500
0!
0(

#603750
1!
1(
b1011 .

#605000
0!
0(

#606250
1!
1(
b1100 .

#607500
0!
0(

#608750
1!
1(
b1101 .

#610000
0!
0(

#611250
1!
1(
b1110 .

#612500
0!
0(

#613750
1!
1(
b1111 .

#615000
0!
0(

#616250
1!
1(
b10000 .

#617500
0!
0(

#618750
1!
1(
b10001 .

#620000
0!
0(

#621250
1!
1(
b10010 .

#622500
0!
0(

#623750
1!
1(
b10011 .

#625000
0!
0(

#626250
1!
1(
b10100 .

#627000
0%
