FPGA/GateKeeper/srcs/GateKeeper.v
`timescale 1ns / 1ps
//////////////////////////////////////////////////////////////////////////////////
// Company: 
// Engineer: 
// 
// Create Date: 03/25/2025 01:38:00 PM
// Design Name: 
// Module Name: GateKeeper
// Project Name: 
// Target Devices: 
// Tool Versions: 
// Description: 
// 
// Dependencies: 
// 
// Revision:
// Revision 0.01 - File Created
// Additional Comments:
// 
//////////////////////////////////////////////////////////////////////////////////


module GateKeeper(
    input wire clk,
    input wire enable,
    input wire [15:0] window,
    input wire [7:0] pulseShaper_width,
    input wire det_in,
    output wire det_out
    );



reg [15:0] c = 16'h0000; // c counts the number of clock cycles since last detection
reg [7:0] c2 = 8'd0; // c2 is used to elongate the pulse width 
reg state = 1'b0; 
reg GateKeeper = 1'b1; // GateKeeper is used to vaariable the output of the module

assign det_out = (GateKeeper) ? det_in:1'b0; // main assignation

//Every 2.5 ns logic is evaluated
always@(posedge clk) begin

    if(enable)begin//from GUI
        case(state)
            0:begin
                if(det_in)begin//input signal
                    if(c<=(window-16'd1))begin // if c is smaller than window (events close to each other)
                        GateKeeper <= 1'd0; // discard det_out
                        state       <= 1; // jump to state 1
                    end
                    c <= {8'd0,pulseShaper_width}; // reset counter every time a detection is made
                end
                else begin
                    c               <= c + 16'h0001; // increment counter whenever there is no detection
                end
            end

            1:begin
                if(c2<(pulseShaper_width-8'd1))begin // keep det_out high for pulseShaper_width clock cycles
                    c2 <= c2 + 8'd1; // increment c2
                end
                else begin // if c2 is equal to pulseShaper_width, reset 
                    c2          <= 8'd0;
                    GateKeeper <= 1'b1; // enable det_out
                    state       <= 0;
                end
            end
        endcase
    end

    else begin // when the module is not enabled, det_in is bypassed to det_out
        GateKeeper             <= 1'b1;// enable det_out
    end

end


endmodule

FPGA/GateKeeper/srcs/tb_GateKeeper.v
`timescale 1ns / 1ps
//////////////////////////////////////////////////////////////////////////////////
// Company: 
// Engineer: 
// 
// Create Date: 03/25/2025 02:57:35 PM
// Design Name: 
// Module Name: tb_GateKeeper
// Project Name: 
// Target Devices: 
// Tool Versions: 
// Description: 
// 
// Dependencies: 
// 
// Revision:
// Revision 0.01 - File Created
// Additional Comments:
// 
//////////////////////////////////////////////////////////////////////////////////


module tb_GateKeeper();
    // Testbench Signals
    reg clk = 0;
    reg enable = 1;
    reg [15:0] window = 16'd6;
    reg [7:0] pulseShaper_width = 8'd4;
    reg det_in = 0;
    wire det_out;
    
    // Clock Generation (400 MHz -> 2.5 ns period)
    always #1.25 clk = ~clk;
    
    // Instantiate DUT (Device Under Test)
    GateKeeper GateKeeper0 (
        .clk(clk),
        .enable(enable),
        .window(window),
        .pulseShaper_width(pulseShaper_width),
        .det_in(det_in),
        .det_out(det_out)
    );
    
    // Stimulus
    initial begin
        $dumpfile("tb_GateKeeper.vcd");
        $dumpvars(0, tb_GateKeeper);
        
        #15;
        det_in = 1;
        #2.5;
        det_in = 0;
        
        #50;
        det_in = 1;
        #2.5;
        det_in = 0;
        
        #10;
        det_in = 1;
        #2.5;
        det_in = 0;

        #1;
        det_in = 1;
        #2.5;
        det_in = 0;

        #1;
        det_in = 1;
        #2.5;
        det_in = 0;
        
        #30;
        det_in = 1;
        #2.5;
        det_in = 0;

        #11.5;
        det_in = 1;
        #2.5;
        det_in = 0;

        #30;
        det_in = 1;
        #2.5;
        det_in = 0;

        #12.5;
        det_in = 1;
        #2.5;
        det_in = 0;

        $finish;
    end
    
endmodule

FPGA/GateKeeper/GateKeeper.sim/sim_1/behav/xsim/tb_GateKeeper.vcd
$date
   Mon Mar 31 21:54:40 2025
$end

$version
  2023.2
  $dumpfile ("tb_GateKeeper.vcd") 
$end

$timescale
  1ps
$end

$scope module tb_GateKeeper $end
$var reg 1 ! clk $end
$var reg 1 " enable $end
$var reg 16 # window [15:0] $end
$var reg 8 $ pulseShaper_width [7:0] $end
$var reg 1 % det_in $end
$var wire 1 & det_out $end
$scope module GateKeeper0 $end
$var wire 1 ' clk $end
$var wire 1 ( enable $end
$var wire 16 ) window [15:0] $end
$var wire 8 * pulseShaper_width [7:0] $end
$var wire 1 + det_in $end
$var wire 1 & det_out $end
$var reg 16 , c [15:0] $end
$var reg 8 - c2 [7:0] $end
$var reg 1 . state $end
$var reg 1 / GateKeeper $end
$upscope $end
$upscope $end
$enddefinitions $end

#0
$dumpvars
0!
1"
b110 #
b100 $
0%
0&
0'
1(
b110 )
b100 *
0+
b0 ,
b0 -
0.
1/
$end

#1250
1!
1'
b1 ,

#2500
0!
0'

#3750
1!
1'
b10 ,

#5000
0!
0'

#6250
1!
1'
b11 ,

#7500
0!
0'

#8750
1!
1'
b100 ,

#10000
0!
0'

#11250
1!
1'
b101 ,

#12500
0!
0'

#13750
1!
1'
b110 ,

#15000
0!
1%
1&
0'
1+

#16250
1!
1'
b100 ,

#17500
0!
0%
0&
0'
0+

#18750
1!
1'
b101 ,

#20000
0!
0'

#21250
1!
1'
b110 ,

#22500
0!
0'

#23750
1!
1'
b111 ,

#25000
0!
0'

#26250
1!
1'
b1000 ,

#27500
0!
0'

#28750
1!
1'
b1001 ,

#30000
0!
0'

#31250
1!
1'
b1010 ,

#32500
0!
0'

#33750
1!
1'
b1011 ,

#35000
0!
0'

#36250
1!
1'
b1100 ,

#37500
0!
0'

#38750
1!
1'
b1101 ,

#40000
0!
0'

#41250
1!
1'
b1110 ,

#42500
0!
0'

#43750
1!
1'
b1111 ,

#45000
0!
0'

#46250
1!
1'
b10000 ,

#47500
0!
0'

#48750
1!
1'
b10001 ,

#50000
0!
0'

#51250
1!
1'
b10010 ,

#52500
0!
0'

#53750
1!
1'
b10011 ,

#55000
0!
0'

#56250
1!
1'
b10100 ,

#57500
0!
0'

#58750
1!
1'
b10101 ,

#60000
0!
0'

#61250
1!
1'
b10110 ,

#62500
0!
0'

#63750
1!
1'
b10111 ,

#65000
0!
0'

#66250
1!
1'
b11000 ,

#67500
0!
1%
1&
0'
1+

#68750
1!
1'
b100 ,

#70000
0!
0%
0&
0'
0+

#71250
1!
1'
b101 ,

#72500
0!
0'

#73750
1!
1'
b110 ,

#75000
0!
0'

#76250
1!
1'
b111 ,

#77500
0!
0'

#78750
1!
1'
b1000 ,

#80000
0!
1%
1&
0'
1+

#81250
1!
1'
b100 ,

#82500
0!
0%
0&
0'
0+

#83500
1%
1&
1+

#83750
1!
0&
1'
1.
0/

#85000
0!
0'

#86000
0%
0+

#86250
1!
1'
b1 -

#87000
1%
1+

#87500
0!
0'

#88750
1!
1'
b10 -

#89500
0%
0+

#90000
0!
0'

#91250
1!
1'
b11 -

#92500
0!
0'

#93750
1!
1'
b0 -
0.
1/

#95000
0!
0'

#96250
1!
1'
b101 ,

#97500
0!
0'

#98750
1!
1'
b110 ,

#100000
0!
0'

#101250
1!
1'
b111 ,

#102500
0!
0'

#103750
1!
1'
b1000 ,

#105000
0!
0'

#106250
1!
1'
b1001 ,

#107500
0!
0'

#108750
1!
1'
b1010 ,

#110000
0!
0'

#111250
1!
1'
b1011 ,

#112500
0!
0'

#113750
1!
1'
b1100 ,

#115000
0!
0'

#116250
1!
1'
b1101 ,

#117500
0!
0'

#118750
1!
1'
b1110 ,

#119500
1%
1&
1+

#120000
0!
0'

#121250
1!
1'
b100 ,

#122000
0%
0&
0+

#122500
0!
0'

#123750
1!
1'
b101 ,

#125000
0!
0'

#126250
1!
1'
b110 ,

#127500
0!
0'

#128750
1!
1'
b111 ,

#130000
0!
0'

#131250
1!
1'
b1000 ,

#132500
0!
0'

#133500
1%
1&
1+

#133750
1!
1'
b100 ,

#135000
0!
0'

#136000
0%
0&
0+

#136250
1!
1'
b101 ,

#137500
0!
0'

#138750
1!
1'
b110 ,

#140000
0!
0'

#141250
1!
1'
b111 ,

#142500
0!
0'

#143750
1!
1'
b1000 ,

#145000
0!
0'

#146250
1!
1'
b1001 ,

#147500
0!
0'

#148750
1!
1'
b1010 ,

#150000
0!
0'

#151250
1!
1'
b1011 ,

#152500
0!
0'

#153750
1!
1'
b1100 ,

#155000
0!
0'

#156250
1!
1'
b1101 ,

#157500
0!
0'

#158750
1!
1'
b1110 ,

#160000
0!
0'

#161250
1!
1'
b1111 ,

#162500
0!
0'

#163750
1!
1'
b10000 ,

#165000
0!
0'

#166000
1%
1&
1+

#166250
1!
1'
b100 ,

#167500
0!
0'

#168500
0%
0&
0+

#168750
1!
1'
b101 ,

#170000
0!
0'

#171250
1!
1'
b110 ,

#172500
0!
0'

#173750
1!
1'
b111 ,

#175000
0!
0'

#176250
1!
1'
b1000 ,

#177500
0!
0'

#178750
1!
1'
b1001 ,

#180000
0!
0'

#181000
1%
1&
1+

#181250
1!
1'
b100 ,

