FPGA/GateKeeper/srcs/GateKeeper.v
`timescale 1ns / 1ps
//////////////////////////////////////////////////////////////////////////////////
// Company: 
// Engineer: 
// 
// Create Date: 03/25/2025 01:38:00 PM
// Design Name: 
// Module Name: GateKeeper
// Project Name: 
// Target Devices: 
// Tool Versions: 
// Description: 
// 
// Dependencies: 
// 
// Revision:
// Revision 0.01 - File Created
// Additional Comments:
// 
//////////////////////////////////////////////////////////////////////////////////


module GateKeeper(
    input wire clk,
    input wire enable,
    input wire [15:0] window,
    input wire [7:0] pulseShaper_width,
    input wire det_in,
    output reg det_out = 1'd0
    );


reg [15:0] c = 16'h0000; // c counts the number of clock cycles since last detection
reg [7:0] c2 = 8'd0; // c2 is used to elongate the pulse width 
reg state = 1'b0; 

//Every 2.5 ns logic is evaluated
always@(posedge clk) begin

    if(enable)begin//from GUI
        case(state)
            0:begin
                if(det_in)begin//input signal
                    if(c>=(window-16'd1))begin // if c is greater than window (events not close to each other)
                        det_out <= 1'd1; // then validate detection
                        state   <= 1; // jump to state 1
                    end
                    else begin
                        det_out <= 1'b0; // if the events are close to each other, then ignore the detection
                    end
                    c <= {8'd0,pulseShaper_width}; // reset counter every time a detection is made
                end
                else begin
                    c <= c + 16'h0001; // increment counter whenever there is no detection
                    det_out <= 1'b0; // output is 0
                end
            end

            1:begin
                if(c2<(pulseShaper_width-8'd1))begin // keep det_out high for pulseShaper_width clock cycles
                    c2 <= c2 + 8'd1; // increment c2
                end
                else begin // if c2 is equal to pulseShaper_width, reset 
                    c2 <= 8'd0;
                    det_out <= 1'b0;
                    state <= 0;
                end
            end
        endcase
    end

    else begin // when the module is not enabled, det_in is bypassed to det_out
        det_out <= det_in;// 50 ns 
    end

end


endmodule

FPGA/GateKeeper/srcs/tb_GateKeeper.v
`timescale 1ns / 1ps
//////////////////////////////////////////////////////////////////////////////////
// Company: 
// Engineer: 
// 
// Create Date: 03/25/2025 02:57:35 PM
// Design Name: 
// Module Name: tb_GateKeeper
// Project Name: 
// Target Devices: 
// Tool Versions: 
// Description: 
// 
// Dependencies: 
// 
// Revision:
// Revision 0.01 - File Created
// Additional Comments:
// 
//////////////////////////////////////////////////////////////////////////////////


module tb_GateKeeper();
    // Testbench Signals
    reg clk = 0;
    reg enable = 1;
    reg [15:0] window = 16'd6;
    reg [7:0] pulseShaper_width = 8'd4;
    reg det_in = 0;
    wire det_out;
    
    // Clock Generation (400 MHz -> 2.5 ns period)
    always #1.25 clk = ~clk;
    
    // Instantiate DUT (Device Under Test)
    GateKeeper GateKeeper0 (
        .clk(clk),
        .enable(enable),
        .window(window),
        .pulseShaper_width(pulseShaper_width),
        .det_in(det_in),
        .det_out(det_out)
    );
    
    // Stimulus
    initial begin
        $dumpfile("tb_GateKeeper.vcd");
        $dumpvars(0, tb_GateKeeper);
        
        #15;
        det_in = 1;
        #2.5;
        det_in = 0;
        
        #50;
        det_in = 1;
        #2.5;
        det_in = 0;
        
        #10;
        det_in = 1;
        #2.5;
        det_in = 0;

        #1;
        det_in = 1;
        #2.5;
        det_in = 0;

        #1;
        det_in = 1;
        #2.5;
        det_in = 0;
        
        #30;
        det_in = 1;
        #2.5;
        det_in = 0;

        #11.5;
        det_in = 1;
        #2.5;
        det_in = 0;

        #30;
        det_in = 1;
        #2.5;
        det_in = 0;

        #12.5;
        det_in = 1;
        #2.5;
        det_in = 0;

        $finish;
    end
    
endmodule

FPGA/GateKeeper/GateKeeper.sim/sim_1/behav/xsim/tb_GateKeeper.vcd
$date
   Tue Mar 25 16:57:36 2025
$end

$version
  2023.2
  $dumpfile ("tb_GateKeeper.vcd") 
$end

$timescale
  1ps
$end

$scope module tb_GateKeeper $end
$var reg 1 ! clk $end
$var reg 1 " enable $end
$var reg 16 # window [15:0] $end
$var reg 8 $ pulseShaper_width [7:0] $end
$var reg 1 % det_in $end
$var wire 1 & det_out $end
$scope module GateKeeper0 $end
$var wire 1 ' clk $end
$var wire 1 ( enable $end
$var wire 16 ) window [15:0] $end
$var wire 8 * pulseShaper_width [7:0] $end
$var wire 1 + det_in $end
$var reg 1 , det_out $end
$var reg 16 - c [15:0] $end
$var reg 8 . c2 [7:0] $end
$var reg 1 / state $end
$upscope $end
$upscope $end
$enddefinitions $end

#0
$dumpvars
0!
1"
b110 #
b100 $
0%
0&
0'
1(
b110 )
b100 *
0+
0,
b0 -
b0 .
0/
$end

#1250
1!
1'
b1 -

#2500
0!
0'

#3750
1!
1'
b10 -

#5000
0!
0'

#6250
1!
1'
b11 -

#7500
0!
0'

#8750
1!
1'
b100 -

#10000
0!
0'

#11250
1!
1'
b101 -

#12500
0!
0'

#13750
1!
1'
b110 -

#15000
0!
1%
0'
1+

#16250
1!
1&
1'
1,
b100 -
1/

#17500
0!
0%
0'
0+

#18750
1!
1'
b1 .

#20000
0!
0'

#21250
1!
1'
b10 .

#22500
0!
0'

#23750
1!
1'
b11 .

#25000
0!
0'

#26250
1!
0&
1'
0,
b0 .
0/

#27500
0!
0'

#28750
1!
1'
b101 -

#30000
0!
0'

#31250
1!
1'
b110 -

#32500
0!
0'

#33750
1!
1'
b111 -

#35000
0!
0'

#36250
1!
1'
b1000 -

#37500
0!
0'

#38750
1!
1'
b1001 -

#40000
0!
0'

#41250
1!
1'
b1010 -

#42500
0!
0'

#43750
1!
1'
b1011 -

#45000
0!
0'

#46250
1!
1'
b1100 -

#47500
0!
0'

#48750
1!
1'
b1101 -

#50000
0!
0'

#51250
1!
1'
b1110 -

#52500
0!
0'

#53750
1!
1'
b1111 -

#55000
0!
0'

#56250
1!
1'
b10000 -

#57500
0!
0'

#58750
1!
1'
b10001 -

#60000
0!
0'

#61250
1!
1'
b10010 -

#62500
0!
0'

#63750
1!
1'
b10011 -

#65000
0!
0'

#66250
1!
1'
b10100 -

#67500
0!
1%
0'
1+

#68750
1!
1&
1'
1,
b100 -
1/

#70000
0!
0%
0'
0+

#71250
1!
1'
b1 .

#72500
0!
0'

#73750
1!
1'
b10 .

#75000
0!
0'

#76250
1!
1'
b11 .

#77500
0!
0'

#78750
1!
0&
1'
0,
b0 .
0/

#80000
0!
1%
0'
1+

#81250
1!
1'

#82500
0!
0%
0'
0+

#83500
1%
1+

#83750
1!
1'

#85000
0!
0'

#86000
0%
0+

#86250
1!
1'
b101 -

#87000
1%
1+

#87500
0!
0'

#88750
1!
1&
1'
1,
b100 -
1/

#89500
0%
0+

#90000
0!
0'

#91250
1!
1'
b1 .

#92500
0!
0'

#93750
1!
1'
b10 .

#95000
0!
0'

#96250
1!
1'
b11 .

#97500
0!
0'

#98750
1!
0&
1'
0,
b0 .
0/

#100000
0!
0'

#101250
1!
1'
b101 -

#102500
0!
0'

#103750
1!
1'
b110 -

#105000
0!
0'

#106250
1!
1'
b111 -

#107500
0!
0'

#108750
1!
1'
b1000 -

#110000
0!
0'

#111250
1!
1'
b1001 -

#112500
0!
0'

#113750
1!
1'
b1010 -

#115000
0!
0'

#116250
1!
1'
b1011 -

#117500
0!
0'

#118750
1!
1'
b1100 -

#119500
1%
1+

#120000
0!
0'

#121250
1!
1&
1'
1,
b100 -
1/

#122000
0%
0+

#122500
0!
0'

#123750
1!
1'
b1 .

#125000
0!
0'

#126250
1!
1'
b10 .

#127500
0!
0'

#128750
1!
1'
b11 .

#130000
0!
0'

#131250
1!
0&
1'
0,
b0 .
0/

#132500
0!
0'

#133500
1%
1+

#133750
1!
1'

#135000
0!
0'

#136000
0%
0+

#136250
1!
1'
b101 -

#137500
0!
0'

#138750
1!
1'
b110 -

#140000
0!
0'

#141250
1!
1'
b111 -

#142500
0!
0'

#143750
1!
1'
b1000 -

#145000
0!
0'

#146250
1!
1'
b1001 -

#147500
0!
0'

#148750
1!
1'
b1010 -

#150000
0!
0'

#151250
1!
1'
b1011 -

#152500
0!
0'

#153750
1!
1'
b1100 -

#155000
0!
0'

#156250
1!
1'
b1101 -

#157500
0!
0'

#158750
1!
1'
b1110 -

#160000
0!
0'

#161250
1!
1'
b1111 -

#162500
0!
0'

#163750
1!
1'
b10000 -

#165000
0!
0'

#166000
1%
1+

#166250
1!
1&
1'
1,
b100 -
1/

#167500
0!
0'

#168500
0%
0+

#168750
1!
1'
b1 .

#170000
0!
0'

#171250
1!
1'
b10 .

#172500
0!
0'

#173750
1!
1'
b11 .

#175000
0!
0'

#176250
1!
0&
1'
0,
b0 .
0/

#177500
0!
0'

#178750
1!
1'
b101 -

#180000
0!
0'

#181000
1%
1+

#181250
1!
1&
1'
1,
b100 -
1/

#182500
0!
0'

#183500
0%
0+

#183750
1!
1'
b1 .

#185000
0!
0'

#186250
1!
1'
b10 .

#187500
0!
0'

#188750
1!
1'
b11 .

#190000
0!
0'

#191250
1!
0&
1'
0,
b0 .
0/

#192500
0!
0'

#193750
1!
1'
b101 -

#195000
0!
0'

#196250
1!
1'
b110 -

#197500
0!
0'

#198750
1!
1'
b111 -

#200000
0!
0'

#201250
1!
1'
b1000 -

#202500
0!
0'

#203750
1!
1'
b1001 -

#205000
0!
0'

#206250
1!
1'
b1010 -

#207500
0!
0'

#208750
1!
1'
b1011 -

#210000
0!
0'

#211250
1!
1'
b1100 -

#212500
0!
0'

#213750
1!
1'
b1101 -

#215000
0!
0'

#216250
1!
1'
b1110 -

#217500
0!
0'

#218750
1!
1'
b1111 -

#220000
0!
0'

#221250
1!
1'
b10000 -

#222500
0!
0'

#223750
1!
1'
b10001 -

#225000
0!
0'

#226250
1!
1'
b10010 -

#227500
0!
0'

#228750
1!
1'
b10011 -

#230000
0!
0'

#231250
1!
1'
b10100 -

#232500
0!
0'

#233750
1!
1'
b10101 -

#235000
0!
0'

#236250
1!
1'
b10110 -

#237500
0!
0'

#238750
1!
1'
b10111 -

#240000
0!
0'

#241250
1!
1'
b11000 -

#242500
0!
0'

#243750
1!
1'
b11001 -

#245000
0!
0'

#246250
1!
1'
b11010 -

#247500
0!
0'

#248750
1!
1'
b11011 -

#250000
0!
0'

#251250
1!
1'
b11100 -

#252500
0!
0'

#253750
1!
1'
b11101 -

#255000
0!
0'

#256250
1!
1'
b11110 -

#257500
0!
0'

#258750
1!
1'
b11111 -

#260000
0!
0'

#261250
1!
1'
b100000 -

